repid_msgspec-0.0.1.dist-info/METADATA
repid_msgspec-0.0.1.dist-info/WHEEL
repid_msgspec-0.0.1.dist-info/entry_points.txt
repid_msgspec-0.0.1.dist-info/licenses/LICENSE
repid_msgspec/__init__.py
repid_msgspec/plugin.py
repid_msgspec-0.0.1.dist-info/RECORD
